{
  "form_title": "FDC Environmental Compliance Monitoring v1.0.0",
  "form_id": "monitoring_form",
  "instance_name": "${form_id}",
  "version": "1.0.0",
  "style": "dynamic-grid",
  "namespaces": "esri=\"https://esri.com/xforms\"",
  "survey": [
    {
      "label": null,
      "label_raw": null,
      "items": [
        {
          "type": "note",
          "name": "form_image",
          "label": "<span>",
          "hint": null,
          "appearance": "w12",
          "required": null,
          "required_message": null,
          "readonly": null,
          "default": null,
          "calculation": null,
          "relevant": null,
          "choice_filter": null,
          "media::image": "header.png",
          "bind::esri:fieldType": null,
          "bind::esri:fieldLength": null,
          "bind::esri:fieldAlias": null,
          "label_raw": "",
          "hint_raw": null
        },
        {
          "type": "text",
          "name": "form_id",
          "label": "<b>Form ID</b><br> <font size=1 color=\"navyblue\">Identifier of the current form. Will be displayed-searchable in Inbox, Outbox and Sent Folders.</font>",
          "hint": null,
          "appearance": "w12 compact",
          "required": null,
          "required_message": null,
          "readonly": "yes",
          "default": null,
          "calculation": "concat(${project_id},\" \",format-date(${monitor_date},'%m/%e/%Y'),\" \",${monitor_name})",
          "relevant": null,
          "choice_filter": null,
          "media::image": null,
          "bind::esri:fieldType": null,
          "bind::esri:fieldLength": 1000.0,
          "bind::esri:fieldAlias": null,
          "label_raw": "Form ID Identifier of the current form. Will be displayed-searchable in Inbox, Outbox and Sent Folders.",
          "hint_raw": null
        },
        {
          "type": "hidden",
          "name": "form_client_name",
          "label": "Client Name",
          "hint": null,
          "appearance": "w12",
          "required": null,
          "required_message": null,
          "readonly": null,
          "default": null,
          "calculation": null,
          "relevant": null,
          "choice_filter": null,
          "media::image": null,
          "bind::esri:fieldType": "esriFieldTypeString",
          "bind::esri:fieldLength": 1000.0,
          "bind::esri:fieldAlias": null,
          "label_raw": "Client Name",
          "hint_raw": null
        },
        {
          "type": "hidden",
          "name": "form_confidentiality",
          "label": "Confidentiality",
          "hint": null,
          "appearance": "w12",
          "required": null,
          "required_message": null,
          "readonly": null,
          "default": "Not Confidential",
          "calculation": null,
          "relevant": null,
          "choice_filter": null,
          "media::image": null,
          "bind::esri:fieldType": "esriFieldTypeString",
          "bind::esri:fieldLength": 1000.0,
          "bind::esri:fieldAlias": null,
          "label_raw": "Confidentiality",
          "hint_raw": null
        },
        {
          "type": "hidden",
          "name": "form_collection",
          "label": "Collection",
          "hint": null,
          "appearance": "w12",
          "required": null,
          "required_message": null,
          "readonly": null,
          "default": "Environmental Compliance",
          "calculation": null,
          "relevant": null,
          "choice_filter": null,
          "media::image": null,
          "bind::esri:fieldType": "esriFieldTypeString",
          "bind::esri:fieldLength": 1000.0,
          "bind::esri:fieldAlias": null,
          "label_raw": "Collection",
          "hint_raw": null
        },
        {
          "type": "hidden",
          "name": "form_service_line",
          "label": "Service Line",
          "hint": null,
          "appearance": "w12",
          "required": null,
          "required_message": null,
          "readonly": null,
          "default": "Environmental Compliance",
          "calculation": null,
          "relevant": null,
          "choice_filter": null,
          "media::image": null,
          "bind::esri:fieldType": "esriFieldTypeString",
          "bind::esri:fieldLength": 1000.0,
          "bind::esri:fieldAlias": null,
          "label_raw": "Service Line",
          "hint_raw": null
        },
        {
          "type": "hidden",
          "name": "form_location",
          "label": "Location of Form",
          "hint": null,
          "appearance": "w12",
          "required": null,
          "required_message": null,
          "readonly": null,
          "default": null,
          "calculation": null,
          "relevant": null,
          "choice_filter": null,
          "media::image": null,
          "bind::esri:fieldType": "esriFieldTypeString",
          "bind::esri:fieldLength": 1000.0,
          "bind::esri:fieldAlias": null,
          "label_raw": "Location of Form",
          "hint_raw": null
        },
        {
          "type": "hidden",
          "name": "form_report_url",
          "label": "Default Report URL",
          "hint": null,
          "appearance": "w12",
          "required": null,
          "required_message": null,
          "readonly": null,
          "default": "1c9ZdbELeO",
          "calculation": null,
          "relevant": null,
          "choice_filter": null,
          "media::image": null,
          "bind::esri:fieldType": "esriFieldTypeString",
          "bind::esri:fieldLength": null,
          "bind::esri:fieldAlias": null,
          "label_raw": "Default Report URL",
          "hint_raw": null
        }
      ]
    },
    {
      "label": "<table cellpadding=5>\n  <tr>\n    <td valign=\"middle\"><img src=\"Databse.svg\"  height=\"35\"></td>\n    <td padding=5>\n      Project Details<br>\n      <font size=1 color=\"navyblue\">Project ID, Project Name</font>\n    </td>\n  </tr>\n</table>\n",
      "label_raw": "Project Details Project ID, Project Name",
      "items": [
        {
          "type": "select_one_from_file vision_projects.csv",
          "name": "project_id",
          "label": "Project Number",
          "hint": "Provide the unique identifier for this project.",
          "appearance": "w6 autocomplete",
          "required": "yes",
          "required_message": "Project Number is Required",
          "readonly": null,
          "default": null,
          "calculation": null,
          "relevant": null,
          "choice_filter": null,
          "media::image": null,
          "bind::esri:fieldType": null,
          "bind::esri:fieldLength": 1000.0,
          "bind::esri:fieldAlias": null,
          "label_raw": "Project Number",
          "hint_raw": "Provide the unique identifier for this project."
        },
        {
          "type": "text",
          "name": "project_name",
          "label": "Project Name ",
          "hint": "Provide the official name of the project.",
          "appearance": "w6",
          "required": null,
          "required_message": null,
          "readonly": "yes",
          "default": null,
          "calculation": "pulldata('vision_projects', 'project_name', 'name', ${project_id})",
          "relevant": null,
          "choice_filter": null,
          "media::image": null,
          "bind::esri:fieldType": null,
          "bind::esri:fieldLength": 1000.0,
          "bind::esri:fieldAlias": null,
          "label_raw": "Project Name",
          "hint_raw": "Provide the official name of the project."
        },
        {
          "type": "select_one_from_file vision_phase.csv",
          "name": "project_phase",
          "label": "Project Phase",
          "hint": null,
          "appearance": "w6 autocomplete",
          "required": null,
          "required_message": null,
          "readonly": null,
          "default": null,
          "calculation": null,
          "relevant": null,
          "choice_filter": "project_id=${project_id}",
          "media::image": null,
          "bind::esri:fieldType": null,
          "bind::esri:fieldLength": null,
          "bind::esri:fieldAlias": null,
          "label_raw": "Project Phase",
          "hint_raw": null
        },
        {
          "type": "select_one_from_file vision_task.csv",
          "name": "project_task",
          "label": "Project Task",
          "hint": null,
          "appearance": "w6 autocomplete",
          "required": null,
          "required_message": null,
          "readonly": null,
          "default": null,
          "calculation": null,
          "relevant": null,
          "choice_filter": "project_id=${project_id} and project_phase=${project_phase}",
          "media::image": null,
          "bind::esri:fieldType": null,
          "bind::esri:fieldLength": null,
          "bind::esri:fieldAlias": null,
          "label_raw": "Project Task",
          "hint_raw": null
        }
      ]
    },
    {
      "label": "<table cellpadding=5>\n  <tr>\n    <td valign=\"middle\"><img src=\"MapLocationDot.svg\"  height=\"35\"></td>\n    <td padding=5>\n      Location Details<br>\n      <font size=1 color=\"navyblue\">Specific Location, General Location, County, State, etc.</font>\n    </td>\n  </tr>\n</table>",
      "label_raw": "Location Details Specific Location, General Location, County, State, etc.",
      "items": [
        {
          "type": "geopoint",
          "name": "location",
          "label": "Form Start Location",
          "hint": null,
          "appearance": "w12",
          "required": null,
          "required_message": null,
          "readonly": null,
          "default": null,
          "calculation": null,
          "relevant": null,
          "choice_filter": null,
          "media::image": null,
          "bind::esri:fieldType": null,
          "bind::esri:fieldLength": null,
          "bind::esri:fieldAlias": null,
          "label_raw": "Form Start Location",
          "hint_raw": null
        },
        {
          "type": "text",
          "name": "loc_project",
          "label": "Specific Location",
          "hint": "The specific location within the primary project area. Auto-filled by field maps when possible.",
          "appearance": "w6 minimal",
          "required": "yes",
          "required_message": null,
          "readonly": null,
          "default": null,
          "calculation": null,
          "relevant": null,
          "choice_filter": null,
          "media::image": null,
          "bind::esri:fieldType": null,
          "bind::esri:fieldLength": null,
          "bind::esri:fieldAlias": null,
          "label_raw": "Specific Location",
          "hint_raw": "The specific location within the primary project area. Auto-filled by field maps when possible."
        },
        {
          "type": "select_one facility_type",
          "name": "loc_type",
          "label": "Location Type",
          "hint": "Indicate the type of location (e.g., structure, pull-site, parcel, culvert, etc.).  Auto-filled by field maps when possible.",
          "appearance": "w6 minimal",
          "required": null,
          "required_message": null,
          "readonly": null,
          "default": null,
          "calculation": null,
          "relevant": null,
          "choice_filter": null,
          "media::image": null,
          "bind::esri:fieldType": null,
          "bind::esri:fieldLength": null,
          "bind::esri:fieldAlias": null,
          "label_raw": "Location Type",
          "hint_raw": "Indicate the type of location (e.g., structure, pull-site, parcel, culvert, etc.). Auto-filled by field maps when possible."
        },
        {
          "type": "text",
          "name": "loc_general",
          "label": "General Location/Area",
          "hint": "Describe the general location or larger area around the site.",
          "appearance": "w12",
          "required": null,
          "required_message": null,
          "readonly": null,
          "default": null,
          "calculation": null,
          "relevant": null,
          "choice_filter": null,
          "media::image": null,
          "bind::esri:fieldType": null,
          "bind::esri:fieldLength": 5000.0,
          "bind::esri:fieldAlias": null,
          "label_raw": "General Location/Area",
          "hint_raw": "Describe the general location or larger area around the site."
        },
        {
          "type": "text",
          "name": "loc_ownership",
          "label": "Ownership",
          "hint": null,
          "appearance": "w6",
          "required": null,
          "required_message": null,
          "readonly": null,
          "default": null,
          "calculation": null,
          "relevant": null,
          "choice_filter": null,
          "media::image": null,
          "bind::esri:fieldType": null,
          "bind::esri:fieldLength": null,
          "bind::esri:fieldAlias": null,
          "label_raw": "Ownership",
          "hint_raw": null
        },
        {
          "type": "text",
          "name": "loc_blm_office",
          "label": "BLM Field Office",
          "hint": null,
          "appearance": "w6",
          "required": null,
          "required_message": null,
          "readonly": null,
          "default": "Rawlins",
          "calculation": null,
          "relevant": null,
          "choice_filter": null,
          "media::image": null,
          "bind::esri:fieldType": null,
          "bind::esri:fieldLength": null,
          "bind::esri:fieldAlias": null,
          "label_raw": "BLM Field Office",
          "hint_raw": null
        },
        {
          "type": "hidden",
          "name": "loc_county",
          "label": "County",
          "hint": "Provide the county where the project is taking place.",
          "appearance": "w6",
          "required": null,
          "required_message": null,
          "readonly": null,
          "default": null,
          "calculation": "pulldata(\"@geopoint\", ${location}, \"reversegeocode.address.Subregion\")",
          "relevant": null,
          "choice_filter": null,
          "media::image": null,
          "bind::esri:fieldType": null,
          "bind::esri:fieldLength": 5000.0,
          "bind::esri:fieldAlias": null,
          "label_raw": "County",
          "hint_raw": "Provide the county where the project is taking place."
        },
        {
          "type": "hidden",
          "name": "loc_state",
          "label": "State",
          "hint": "Provide the state where the project is situated.",
          "appearance": "w6",
          "required": null,
          "required_message": null,
          "readonly": null,
          "default": null,
          "calculation": "pulldata(\"@geopoint\", ${location}, \"reversegeocode.address.Region\")",
          "relevant": null,
          "choice_filter": null,
          "media::image": null,
          "bind::esri:fieldType": null,
          "bind::esri:fieldLength": 5000.0,
          "bind::esri:fieldAlias": null,
          "label_raw": "State",
          "hint_raw": "Provide the state where the project is situated."
        },
        {
          "type": "decimal",
          "name": "loc_utm_zone",
          "label": "UTM Zone",
          "hint": null,
          "appearance": "w4",
          "required": null,
          "required_message": null,
          "readonly": "yes",
          "default": null,
          "calculation": "pulldata(\"@geopoint\", ${location}, \"UTM.zone\")",
          "relevant": null,
          "choice_filter": null,
          "media::image": null,
          "bind::esri:fieldType": null,
          "bind::esri:fieldLength": null,
          "bind::esri:fieldAlias": null,
          "label_raw": "UTM Zone",
          "hint_raw": null
        },
        {
          "type": "decimal",
          "name": "loc_utm_x",
          "label": "Easting",
          "hint": null,
          "appearance": "w4",
          "required": null,
          "required_message": null,
          "readonly": "yes",
          "default": null,
          "calculation": "pulldata(\"@geopoint\", ${location}, \"UTM.easting\", 0.00001)",
          "relevant": null,
          "choice_filter": null,
          "media::image": null,
          "bind::esri:fieldType": null,
          "bind::esri:fieldLength": null,
          "bind::esri:fieldAlias": null,
          "label_raw": "Easting",
          "hint_raw": null
        },
        {
          "type": "decimal",
          "name": "loc_utm_y",
          "label": "Northing",
          "hint": null,
          "appearance": "w4",
          "required": null,
          "required_message": null,
          "readonly": "yes",
          "default": null,
          "calculation": "pulldata(\"@geopoint\", ${location}, \"UTM.northing\", 0.00001)",
          "relevant": null,
          "choice_filter": null,
          "media::image": null,
          "bind::esri:fieldType": null,
          "bind::esri:fieldLength": null,
          "bind::esri:fieldAlias": null,
          "label_raw": "Northing",
          "hint_raw": null
        }
      ]
    },
    {
      "label": "<table cellpadding=5>\n  <tr>\n    <td valign=\"middle\"><img src=\"UserClock.svg\"  height=\"35\"></td>\n    <td padding=5>\n      Monitoring/Inspection Details<br>\n      <font size=1 color=\"navyblue\">Dates/Times, Total Hours, Weather, etc.</font>\n    </td>\n  </tr>\n</table>",
      "label_raw": "Monitoring/Inspection Details Dates/Times, Total Hours, Weather, etc.",
      "items": [
        {
          "label": "Name/Date/Activities",
          "label_raw": "Name/Date/Activities",
          "items": [
            {
              "type": "text",
              "name": "monitor_name",
              "label": "Monitor Name",
              "hint": "Insert the name of the person or team monitoring the project.",
              "appearance": "w6",
              "required": "yes",
              "required_message": null,
              "readonly": null,
              "default": null,
              "calculation": "pulldata(\"@property\",\"userFullName\")",
              "relevant": null,
              "choice_filter": null,
              "media::image": null,
              "bind::esri:fieldType": null,
              "bind::esri:fieldLength": 5000.0,
              "bind::esri:fieldAlias": null,
              "label_raw": "Monitor Name",
              "hint_raw": "Insert the name of the person or team monitoring the project."
            },
            {
              "type": "date",
              "name": "monitor_date",
              "label": "Date of Monitoring/Inspection",
              "hint": "Select the date when the monitoring was conducted.",
              "appearance": "w6",
              "required": "yes",
              "required_message": null,
              "readonly": null,
              "default": null,
              "calculation": "now()",
              "relevant": null,
              "choice_filter": null,
              "media::image": null,
              "bind::esri:fieldType": null,
              "bind::esri:fieldLength": null,
              "bind::esri:fieldAlias": null,
              "label_raw": "Date of Monitoring/Inspection",
              "hint_raw": "Select the date when the monitoring was conducted."
            },
            {
              "type": "select_one monitoring_type",
              "name": "monitor_type",
              "label": "Monitoring/Inspection Type",
              "hint": "Additional Section will appear based on choice",
              "appearance": "w12 compact-2",
              "required": "yes",
              "required_message": null,
              "readonly": null,
              "default": null,
              "calculation": null,
              "relevant": null,
              "choice_filter": null,
              "media::image": null,
              "bind::esri:fieldType": null,
              "bind::esri:fieldLength": null,
              "bind::esri:fieldAlias": null,
              "label_raw": "Monitoring/Inspection Type",
              "hint_raw": "Additional Section will appear based on choice"
            }
          ]
        },
        {
          "type": "end group",
          "name": "monitor_details",
          "label": "monitor_details",
          "hint": null,
          "appearance": null,
          "required": null,
          "required_message": null,
          "readonly": null,
          "default": null,
          "calculation": null,
          "relevant": null,
          "choice_filter": null,
          "media::image": null,
          "bind::esri:fieldType": null,
          "bind::esri:fieldLength": null,
          "bind::esri:fieldAlias": null,
          "label_raw": "monitor_details",
          "hint_raw": null
        },
        {
          "label": "Weather",
          "label_raw": "Weather",
          "items": [
            {
              "type": "select_one weather_sky",
              "name": "weather_sky",
              "label": "Sky Conditions",
              "hint": "Describe the general weather conditions during the monitoring.",
              "appearance": "w6 minimal",
              "required": null,
              "required_message": null,
              "readonly": null,
              "default": null,
              "calculation": null,
              "relevant": null,
              "choice_filter": null,
              "media::image": null,
              "bind::esri:fieldType": null,
              "bind::esri:fieldLength": null,
              "bind::esri:fieldAlias": null,
              "label_raw": "Sky Conditions",
              "hint_raw": "Describe the general weather conditions during the monitoring."
            },
            {
              "type": "select_one weather_ground",
              "name": "weather_ground",
              "label": "Ground Conditions",
              "hint": "<p>",
              "appearance": "w6 minimal",
              "required": null,
              "required_message": null,
              "readonly": null,
              "default": null,
              "calculation": null,
              "relevant": null,
              "choice_filter": null,
              "media::image": null,
              "bind::esri:fieldType": null,
              "bind::esri:fieldLength": null,
              "bind::esri:fieldAlias": null,
              "label_raw": "Ground Conditions",
              "hint_raw": ""
            },
            {
              "type": "select_one weather_wind",
              "name": "weather_wind",
              "label": "Wind Conditions",
              "hint": "Note the wind speed during monitoring.",
              "appearance": "w6 minimal",
              "required": null,
              "required_message": null,
              "readonly": null,
              "default": null,
              "calculation": null,
              "relevant": null,
              "choice_filter": null,
              "media::image": null,
              "bind::esri:fieldType": null,
              "bind::esri:fieldLength": null,
              "bind::esri:fieldAlias": null,
              "label_raw": "Wind Conditions",
              "hint_raw": "Note the wind speed during monitoring."
            },
            {
              "type": "decimal",
              "name": "weather_temperature",
              "label": "Temperature (F)",
              "hint": "Note down the temperature at the time of monitoring.",
              "appearance": "w6 minimal",
              "required": null,
              "required_message": null,
              "readonly": null,
              "default": null,
              "calculation": null,
              "relevant": null,
              "choice_filter": null,
              "media::image": null,
              "bind::esri:fieldType": null,
              "bind::esri:fieldLength": null,
              "bind::esri:fieldAlias": null,
              "label_raw": "Temperature (F)",
              "hint_raw": "Note down the temperature at the time of monitoring."
            }
          ]
        },
        {
          "type": "end group",
          "name": "weather",
          "label": "weather",
          "hint": null,
          "appearance": null,
          "required": null,
          "required_message": null,
          "readonly": null,
          "default": null,
          "calculation": null,
          "relevant": null,
          "choice_filter": null,
          "media::image": null,
          "bind::esri:fieldType": null,
          "bind::esri:fieldLength": null,
          "bind::esri:fieldAlias": null,
          "label_raw": "weather",
          "hint_raw": null
        }
      ]
    },
    {
      "label": "<table cellpadding=5>\n  <tr>\n    <td valign=\"middle\"><img src=\"Hammer.svg\"  height=\"35\"></td>\n    <td padding=5>\n      Construction Details<br>\n      <font size=1 color=\"navyblue\">Company, Foreman, Activites, etc.</font>\n    </td>\n  </tr>\n</table>",
      "label_raw": "Construction Details Company, Foreman, Activites, etc.",
      "items": [
        {
          "label": "Construction Details",
          "label_raw": "Construction Details",
          "items": [
            {
              "type": "text",
              "name": "company",
              "label": "Company",
              "hint": "Name the construction company involved in the project.",
              "appearance": "w12",
              "required": null,
              "required_message": null,
              "readonly": null,
              "default": "BWJV",
              "calculation": null,
              "relevant": null,
              "choice_filter": null,
              "media::image": null,
              "bind::esri:fieldType": null,
              "bind::esri:fieldLength": 5000.0,
              "bind::esri:fieldAlias": null,
              "label_raw": "Company",
              "hint_raw": "Name the construction company involved in the project."
            },
            {
              "type": "hidden",
              "name": "foreman",
              "label": "Foreman",
              "hint": "Provide the foreman's name who is supervising the project.",
              "appearance": "w6",
              "required": null,
              "required_message": null,
              "readonly": null,
              "default": null,
              "calculation": null,
              "relevant": null,
              "choice_filter": null,
              "media::image": null,
              "bind::esri:fieldType": null,
              "bind::esri:fieldLength": 5000.0,
              "bind::esri:fieldAlias": null,
              "label_raw": "Foreman",
              "hint_raw": "Provide the foreman's name who is supervising the project."
            },
            {
              "type": "select_one construction_activities",
              "name": "construction_activity",
              "label": "Construction Activity",
              "hint": null,
              "appearance": "w12 horizontal",
              "required": null,
              "required_message": null,
              "readonly": null,
              "default": null,
              "calculation": null,
              "relevant": null,
              "choice_filter": null,
              "media::image": null,
              "bind::esri:fieldType": null,
              "bind::esri:fieldLength": null,
              "bind::esri:fieldAlias": null,
              "label_raw": "Construction Activity",
              "hint_raw": null
            },
            {
              "type": "select_multiple construction_activites_specific",
              "name": "construction_activites_specific",
              "label": "Specific Construction Activities",
              "hint": "List the construction activities taking place.",
              "appearance": "w12 minimal",
              "required": null,
              "required_message": null,
              "readonly": null,
              "default": null,
              "calculation": null,
              "relevant": "${construction_activity}!=\"\"",
              "choice_filter": "category=${construction_activity}",
              "media::image": null,
              "bind::esri:fieldType": null,
              "bind::esri:fieldLength": null,
              "bind::esri:fieldAlias": null,
              "label_raw": "Specific Construction Activities",
              "hint_raw": "List the construction activities taking place."
            },
            {
              "type": "select_multiple construction_equipment",
              "name": "construction_equipment",
              "label": "Construction Equipment",
              "hint": "Describe the equipment being used for construction.",
              "appearance": "w12 compact-2",
              "required": null,
              "required_message": null,
              "readonly": null,
              "default": null,
              "calculation": null,
              "relevant": null,
              "choice_filter": null,
              "media::image": null,
              "bind::esri:fieldType": null,
              "bind::esri:fieldLength": 5000.0,
              "bind::esri:fieldAlias": null,
              "label_raw": "Construction Equipment",
              "hint_raw": "Describe the equipment being used for construction."
            },
            {
              "type": "text",
              "name": "construction_other",
              "label": "Other Activites/Equipment",
              "hint": "Include any other activities or equipment not previously listed.",
              "appearance": "w12",
              "required": null,
              "required_message": null,
              "readonly": null,
              "default": null,
              "calculation": null,
              "relevant": "selected(${construction_activity} ,\"other\") or selected(${construction_equipment} ,\"other\")",
              "choice_filter": null,
              "media::image": null,
              "bind::esri:fieldType": null,
              "bind::esri:fieldLength": 5000.0,
              "bind::esri:fieldAlias": null,
              "label_raw": "Other Activites/Equipment",
              "hint_raw": "Include any other activities or equipment not previously listed."
            }
          ]
        },
        {
          "type": "end group",
          "name": "construction_activites",
          "label": "construction_activites",
          "hint": null,
          "appearance": null,
          "required": null,
          "required_message": null,
          "readonly": null,
          "default": null,
          "calculation": null,
          "relevant": null,
          "choice_filter": null,
          "media::image": null,
          "bind::esri:fieldType": null,
          "bind::esri:fieldLength": null,
          "bind::esri:fieldAlias": null,
          "label_raw": "construction_activites",
          "hint_raw": null
        }
      ]
    },
    {
      "label": "<table cellpadding=5>\n  <tr>\n    <td valign=\"middle\"><img src=\"TriangleExclamation.svg\"  height=\"35\"></td>\n    <td padding=5>\n      Compliance/Permit Conditions<br>\n      <font size=1 color=\"navyblue\">Compliance Categories, Description, Who was notified, etc.</font>\n    </td>\n  </tr>\n</table>",
      "label_raw": "Compliance/Permit Conditions Compliance Categories, Description, Who was notified, etc.",
      "items": [
        {
          "label": "Information and IDs",
          "label_raw": "Information and IDs",
          "items": [
            {
              "type": "select_one compliance_level",
              "name": "compliance_level",
              "label": "Compliance Level",
              "hint": null,
              "appearance": "w12 compact-2",
              "required": "yes",
              "required_message": null,
              "readonly": null,
              "default": null,
              "calculation": null,
              "relevant": null,
              "choice_filter": null,
              "media::image": null,
              "bind::esri:fieldType": null,
              "bind::esri:fieldLength": null,
              "bind::esri:fieldAlias": null,
              "label_raw": "Compliance Level",
              "hint_raw": null
            },
            {
              "type": "text",
              "name": "compliance_level_desc",
              "label": "Description of Compliance Level",
              "hint": null,
              "appearance": "w12 multiline predictivetext",
              "required": null,
              "required_message": null,
              "readonly": null,
              "default": null,
              "calculation": null,
              "relevant": null,
              "choice_filter": null,
              "media::image": null,
              "bind::esri:fieldType": null,
              "bind::esri:fieldLength": null,
              "bind::esri:fieldAlias": null,
              "label_raw": "Description of Compliance Level",
              "hint_raw": null
            },
            {
              "type": "text",
              "name": "monitor_desc",
              "label": "Description of Monitoring/Inspection",
              "hint": null,
              "appearance": "w12 multiline predictivetext",
              "required": "yes",
              "required_message": null,
              "readonly": null,
              "default": null,
              "calculation": null,
              "relevant": null,
              "choice_filter": null,
              "media::image": null,
              "bind::esri:fieldType": null,
              "bind::esri:fieldLength": 5000.0,
              "bind::esri:fieldAlias": null,
              "label_raw": "Description of Monitoring/Inspection",
              "hint_raw": null
            },
            {
              "type": "select_one scope_id",
              "name": "scope_id",
              "label": "Scope of Work ID",
              "hint": null,
              "appearance": "w6 minimal",
              "required": null,
              "required_message": null,
              "readonly": null,
              "default": "SOW1",
              "calculation": null,
              "relevant": null,
              "choice_filter": null,
              "media::image": null,
              "bind::esri:fieldType": null,
              "bind::esri:fieldLength": null,
              "bind::esri:fieldAlias": null,
              "label_raw": "Scope of Work ID",
              "hint_raw": null
            },
            {
              "type": "hidden",
              "name": "compliance_number",
              "label": "Compliance Number",
              "hint": null,
              "appearance": "w6",
              "required": null,
              "required_message": null,
              "readonly": null,
              "default": null,
              "calculation": null,
              "relevant": null,
              "choice_filter": null,
              "media::image": null,
              "bind::esri:fieldType": null,
              "bind::esri:fieldLength": null,
              "bind::esri:fieldAlias": null,
              "label_raw": "Compliance Number",
              "hint_raw": null
            },
            {
              "type": "select_multiple inpsection_relation",
              "name": "compliance_related",
              "label": "Is this inspection related to any of the following?",
              "hint": null,
              "appearance": "w12 compact-2",
              "required": null,
              "required_message": null,
              "readonly": null,
              "default": null,
              "calculation": null,
              "relevant": null,
              "choice_filter": null,
              "media::image": null,
              "bind::esri:fieldType": null,
              "bind::esri:fieldLength": null,
              "bind::esri:fieldAlias": null,
              "label_raw": "Is this inspection related to any of the following?",
              "hint_raw": null
            },
            {
              "type": "text",
              "name": "variance_id",
              "label": "Variance ID",
              "hint": null,
              "appearance": "w12",
              "required": "yes",
              "required_message": null,
              "readonly": null,
              "default": null,
              "calculation": null,
              "relevant": "selected(${compliance_related},'Variance')",
              "choice_filter": null,
              "media::image": null,
              "bind::esri:fieldType": null,
              "bind::esri:fieldLength": null,
              "bind::esri:fieldAlias": null,
              "label_raw": "Variance ID",
              "hint_raw": null
            },
            {
              "type": "text",
              "name": "change_id",
              "label": "Change ID",
              "hint": null,
              "appearance": "w12",
              "required": "yes",
              "required_message": null,
              "readonly": null,
              "default": null,
              "calculation": null,
              "relevant": "selected(${compliance_related},'Change')",
              "choice_filter": null,
              "media::image": null,
              "bind::esri:fieldType": null,
              "bind::esri:fieldLength": null,
              "bind::esri:fieldAlias": null,
              "label_raw": "Change ID",
              "hint_raw": null
            },
            {
              "type": "text",
              "name": "deviation_id_ps",
              "label": "Deviation ID (Private/State)",
              "hint": null,
              "appearance": "w12",
              "required": "yes",
              "required_message": null,
              "readonly": null,
              "default": null,
              "calculation": null,
              "relevant": "selected(${compliance_related},'Deviation_Private_State')",
              "choice_filter": null,
              "media::image": null,
              "bind::esri:fieldType": null,
              "bind::esri:fieldLength": null,
              "bind::esri:fieldAlias": null,
              "label_raw": "Deviation ID (Private/State)",
              "hint_raw": null
            },
            {
              "type": "text",
              "name": "devation_id",
              "label": "Deviation ID (BLM)",
              "hint": null,
              "appearance": "w12",
              "required": "yes",
              "required_message": null,
              "readonly": null,
              "default": null,
              "calculation": null,
              "relevant": "selected(${compliance_related},'Deviation_Federal')",
              "choice_filter": null,
              "media::image": null,
              "bind::esri:fieldType": null,
              "bind::esri:fieldLength": null,
              "bind::esri:fieldAlias": null,
              "label_raw": "Deviation ID (BLM)",
              "hint_raw": null
            },
            {
              "type": "text",
              "name": "exception_id",
              "label": "Exception ID",
              "hint": null,
              "appearance": "w12",
              "required": "yes",
              "required_message": null,
              "readonly": null,
              "default": null,
              "calculation": null,
              "relevant": "selected(${compliance_related},'Exception')",
              "choice_filter": null,
              "media::image": null,
              "bind::esri:fieldType": null,
              "bind::esri:fieldLength": null,
              "bind::esri:fieldAlias": null,
              "label_raw": "Exception ID",
              "hint_raw": null
            },
            {
              "type": "text",
              "name": "refi_id",
              "label": "RFI",
              "hint": null,
              "appearance": "w12",
              "required": "yes",
              "required_message": null,
              "readonly": null,
              "default": null,
              "calculation": null,
              "relevant": "selected(${compliance_related},'RFI')",
              "choice_filter": null,
              "media::image": null,
              "bind::esri:fieldType": null,
              "bind::esri:fieldLength": null,
              "bind::esri:fieldAlias": null,
              "label_raw": "RFI",
              "hint_raw": null
            },
            {
              "type": "text",
              "name": "compliance_related_desc",
              "label": "Summary of Related Items",
              "hint": null,
              "appearance": "w12",
              "required": "yes",
              "required_message": null,
              "readonly": null,
              "default": null,
              "calculation": null,
              "relevant": "${compliance_related}!=\"\"",
              "choice_filter": null,
              "media::image": null,
              "bind::esri:fieldType": null,
              "bind::esri:fieldLength": null,
              "bind::esri:fieldAlias": null,
              "label_raw": "Summary of Related Items",
              "hint_raw": null
            }
          ]
        },
        {
          "type": "end group",
          "name": "inspection_details",
          "label": "inspection_details",
          "hint": null,
          "appearance": null,
          "required": null,
          "required_message": null,
          "readonly": null,
          "default": null,
          "calculation": null,
          "relevant": null,
          "choice_filter": null,
          "media::image": null,
          "bind::esri:fieldType": null,
          "bind::esri:fieldLength": null,
          "bind::esri:fieldAlias": null,
          "label_raw": "inspection_details",
          "hint_raw": null
        },
        {
          "type": "begin repeat",
          "name": "permit_conditions",
          "label": "Permit Conditions ",
          "hint": null,
          "appearance": "w12 compact",
          "required": null,
          "required_message": null,
          "readonly": null,
          "default": null,
          "calculation": null,
          "relevant": null,
          "choice_filter": null,
          "media::image": null,
          "bind::esri:fieldType": null,
          "bind::esri:fieldLength": null,
          "bind::esri:fieldAlias": null,
          "label_raw": "Permit Conditions",
          "hint_raw": null
        },
        {
          "type": "select_one compliance_category_2",
          "name": "permit_category",
          "label": "Category",
          "hint": null,
          "appearance": "w6 minimal",
          "required": null,
          "required_message": null,
          "readonly": null,
          "default": null,
          "calculation": null,
          "relevant": null,
          "choice_filter": null,
          "media::image": null,
          "bind::esri:fieldType": null,
          "bind::esri:fieldLength": null,
          "bind::esri:fieldAlias": null,
          "label_raw": "Category",
          "hint_raw": null
        },
        {
          "type": "hidden",
          "name": "permit_search",
          "label": "Search Term",
          "hint": null,
          "appearance": "w6",
          "required": null,
          "required_message": null,
          "readonly": null,
          "default": null,
          "calculation": null,
          "relevant": null,
          "choice_filter": null,
          "media::image": null,
          "bind::esri:fieldType": null,
          "bind::esri:fieldLength": null,
          "bind::esri:fieldAlias": null,
          "label_raw": "Search Term",
          "hint_raw": null
        },
        {
          "type": "text",
          "name": "permit_constraints",
          "label": "Select Constraints",
          "hint": null,
          "appearance": "w12 multiline",
          "required": null,
          "required_message": null,
          "readonly": null,
          "default": null,
          "calculation": null,
          "relevant": null,
          "choice_filter": null,
          "media::image": null,
          "bind::esri:fieldType": null,
          "bind::esri:fieldLength": 5000000.0,
          "bind::esri:fieldAlias": null,
          "label_raw": "Select Constraints",
          "hint_raw": null
        },
        {
          "type": "end repeat",
          "name": "permit_conditions",
          "label": "permit_conditions",
          "hint": null,
          "appearance": null,
          "required": null,
          "required_message": null,
          "readonly": null,
          "default": null,
          "calculation": null,
          "relevant": null,
          "choice_filter": null,
          "media::image": null,
          "bind::esri:fieldType": null,
          "bind::esri:fieldLength": null,
          "bind::esri:fieldAlias": null,
          "label_raw": "permit_conditions",
          "hint_raw": null
        }
      ]
    },
    {
      "label": "<table cellpadding=5>\n  <tr>\n    <td valign=\"middle\"><img src=\"addForms.svg\"  height=\"35\"></td>\n    <td padding=5>\n      Natural Resources<br>\n      <font size=1 color=\"navyblue\">SS Species, Habitat, Action Taken, etc.</font>\n    </td>\n  </tr>\n</table>",
      "label_raw": "Natural Resources SS Species, Habitat, Action Taken, etc.",
      "items": [
        {
          "label": "<p>",
          "label_raw": "",
          "items": [
            {
              "type": "select_one yes_no",
              "name": "nr_survey_yn",
              "label": "Were any biological surveys completed?",
              "hint": null,
              "appearance": "w12 horizontal",
              "required": null,
              "required_message": null,
              "readonly": null,
              "default": null,
              "calculation": null,
              "relevant": null,
              "choice_filter": null,
              "media::image": null,
              "bind::esri:fieldType": null,
              "bind::esri:fieldLength": null,
              "bind::esri:fieldAlias": "NR Present",
              "label_raw": "Were any biological surveys completed?",
              "hint_raw": null
            },
            {
              "type": "text",
              "name": "nr_species_to_survey",
              "label": "Sensitive Species Surveyed for",
              "hint": "include summary of all sensitive animal and plant species observations, if any",
              "appearance": "w12 predictivetext",
              "required": null,
              "required_message": null,
              "readonly": null,
              "default": null,
              "calculation": null,
              "relevant": "${nr_survey_yn}=\"yes\"",
              "choice_filter": null,
              "media::image": null,
              "bind::esri:fieldType": null,
              "bind::esri:fieldLength": null,
              "bind::esri:fieldAlias": null,
              "label_raw": "Sensitive Species Surveyed for",
              "hint_raw": "include summary of all sensitive animal and plant species observations, if any"
            },
            {
              "type": "select_one yes_no",
              "name": "nr_resources_yn",
              "label": "Were any biological resources observed?",
              "hint": null,
              "appearance": "w6 horizontal",
              "required": null,
              "required_message": null,
              "readonly": null,
              "default": null,
              "calculation": null,
              "relevant": "${nr_survey_yn}=\"yes\"",
              "choice_filter": null,
              "media::image": null,
              "bind::esri:fieldType": null,
              "bind::esri:fieldLength": null,
              "bind::esri:fieldAlias": null,
              "label_raw": "Were any biological resources observed?",
              "hint_raw": null
            }
          ]
        },
        {
          "type": "end group",
          "name": "natural_resources_info",
          "label": "natural_resources_info",
          "hint": null,
          "appearance": null,
          "required": null,
          "required_message": null,
          "readonly": null,
          "default": null,
          "calculation": null,
          "relevant": null,
          "choice_filter": null,
          "media::image": null,
          "bind::esri:fieldType": null,
          "bind::esri:fieldLength": null,
          "bind::esri:fieldAlias": null,
          "label_raw": "natural_resources_info",
          "hint_raw": null
        },
        {
          "label": "Biological Resources Observed",
          "label_raw": "Biological Resources Observed",
          "items": [
            {
              "type": "text",
              "name": "nr_name",
              "label": "Description of Resources",
              "hint": "Include observed resources, habitat, health, etc.",
              "appearance": "w12 multiline autocomplete",
              "required": null,
              "required_message": null,
              "readonly": null,
              "default": null,
              "calculation": null,
              "relevant": null,
              "choice_filter": null,
              "media::image": null,
              "bind::esri:fieldType": null,
              "bind::esri:fieldLength": 5000.0,
              "bind::esri:fieldAlias": null,
              "label_raw": "Description of Resources",
              "hint_raw": "Include observed resources, habitat, health, etc."
            },
            {
              "type": "text",
              "name": "nr_protection",
              "label": "Compliance Measures",
              "hint": null,
              "appearance": "w12 multiline autocomplete",
              "required": null,
              "required_message": null,
              "readonly": null,
              "default": null,
              "calculation": null,
              "relevant": null,
              "choice_filter": null,
              "media::image": null,
              "bind::esri:fieldType": null,
              "bind::esri:fieldLength": 5000.0,
              "bind::esri:fieldAlias": null,
              "label_raw": "Compliance Measures",
              "hint_raw": null
            },
            {
              "type": "text",
              "name": "nr_notify_name",
              "label": "Who was notified?",
              "hint": null,
              "appearance": "w6",
              "required": null,
              "required_message": null,
              "readonly": null,
              "default": null,
              "calculation": null,
              "relevant": null,
              "choice_filter": null,
              "media::image": null,
              "bind::esri:fieldType": null,
              "bind::esri:fieldLength": null,
              "bind::esri:fieldAlias": null,
              "label_raw": "Who was notified?",
              "hint_raw": null
            },
            {
              "type": "dateTime",
              "name": "nr_notify_time",
              "label": "When were they notified?",
              "hint": null,
              "appearance": "w6",
              "required": null,
              "required_message": null,
              "readonly": null,
              "default": null,
              "calculation": "now()",
              "relevant": null,
              "choice_filter": null,
              "media::image": null,
              "bind::esri:fieldType": null,
              "bind::esri:fieldLength": null,
              "bind::esri:fieldAlias": null,
              "label_raw": "When were they notified?",
              "hint_raw": null
            },
            {
              "type": "text",
              "name": "nr_notify_notes",
              "label": "Notification Notes",
              "hint": null,
              "appearance": "w12 multiline autocomplete",
              "required": null,
              "required_message": null,
              "readonly": null,
              "default": null,
              "calculation": null,
              "relevant": null,
              "choice_filter": null,
              "media::image": null,
              "bind::esri:fieldType": null,
              "bind::esri:fieldLength": 5000.0,
              "bind::esri:fieldAlias": null,
              "label_raw": "Notification Notes",
              "hint_raw": null
            }
          ]
        },
        {
          "type": "end group",
          "name": "species_observations",
          "label": "species_observations",
          "hint": null,
          "appearance": null,
          "required": null,
          "required_message": null,
          "readonly": null,
          "default": null,
          "calculation": null,
          "relevant": null,
          "choice_filter": null,
          "media::image": null,
          "bind::esri:fieldType": null,
          "bind::esri:fieldLength": null,
          "bind::esri:fieldAlias": null,
          "label_raw": "species_observations",
          "hint_raw": null
        }
      ]
    },
    {
      "label": "<table cellpadding=5>\n  <tr>\n    <td valign=\"middle\"><img src=\"addForms.svg\"  height=\"35\"></td>\n    <td padding=5>\n      Cultural Resources<br>\n      <font size=1 color=\"navyblue\">Discovery, Protections, Notifications</font>\n    </td>\n  </tr>\n</table>",
      "label_raw": "Cultural Resources Discovery, Protections, Notifications",
      "items": [
        {
          "type": "select_one yes_no",
          "name": "cr_yn",
          "label": "Were cultural remains exposed during construction activities?",
          "hint": null,
          "appearance": "w1 horizontal",
          "required": null,
          "required_message": null,
          "readonly": null,
          "default": null,
          "calculation": null,
          "relevant": null,
          "choice_filter": null,
          "media::image": null,
          "bind::esri:fieldType": null,
          "bind::esri:fieldLength": null,
          "bind::esri:fieldAlias": "CR Present",
          "label_raw": "Were cultural remains exposed during construction activities?",
          "hint_raw": null
        },
        {
          "label": "<p>",
          "label_raw": "",
          "items": [
            {
              "type": "text",
              "name": "cr_description",
              "label": "Description of Discovery",
              "hint": "Include relevant site or feature id(s)",
              "appearance": "w12 multiline predictivetext",
              "required": null,
              "required_message": null,
              "readonly": null,
              "default": null,
              "calculation": null,
              "relevant": null,
              "choice_filter": null,
              "media::image": null,
              "bind::esri:fieldType": null,
              "bind::esri:fieldLength": 5000.0,
              "bind::esri:fieldAlias": null,
              "label_raw": "Description of Discovery",
              "hint_raw": "Include relevant site or feature id(s)"
            },
            {
              "type": "select_multiple existing_protection",
              "name": "cr_protection",
              "label": "Discovery Protection",
              "hint": null,
              "appearance": "w12 compact-2",
              "required": null,
              "required_message": null,
              "readonly": null,
              "default": null,
              "calculation": null,
              "relevant": null,
              "choice_filter": null,
              "media::image": null,
              "bind::esri:fieldType": null,
              "bind::esri:fieldLength": null,
              "bind::esri:fieldAlias": null,
              "label_raw": "Discovery Protection",
              "hint_raw": null
            },
            {
              "type": "text",
              "name": "cr_protection_other",
              "label": "Other Protection(s)",
              "hint": null,
              "appearance": "w12 multiline predictivetext",
              "required": null,
              "required_message": null,
              "readonly": null,
              "default": null,
              "calculation": null,
              "relevant": "selected(${cr_protection},\"other\")",
              "choice_filter": null,
              "media::image": null,
              "bind::esri:fieldType": null,
              "bind::esri:fieldLength": 5000.0,
              "bind::esri:fieldAlias": null,
              "label_raw": "Other Protection(s)",
              "hint_raw": null
            },
            {
              "type": "text",
              "name": "cr_notify_name",
              "label": "Who was notified?",
              "hint": null,
              "appearance": "w6",
              "required": null,
              "required_message": null,
              "readonly": null,
              "default": null,
              "calculation": null,
              "relevant": null,
              "choice_filter": null,
              "media::image": null,
              "bind::esri:fieldType": null,
              "bind::esri:fieldLength": 5000.0,
              "bind::esri:fieldAlias": null,
              "label_raw": "Who was notified?",
              "hint_raw": null
            },
            {
              "type": "dateTime",
              "name": "cr_notify_time",
              "label": "When were they notified?",
              "hint": null,
              "appearance": "w6",
              "required": null,
              "required_message": null,
              "readonly": null,
              "default": null,
              "calculation": null,
              "relevant": null,
              "choice_filter": null,
              "media::image": null,
              "bind::esri:fieldType": null,
              "bind::esri:fieldLength": null,
              "bind::esri:fieldAlias": null,
              "label_raw": "When were they notified?",
              "hint_raw": null
            },
            {
              "type": "text",
              "name": "cr_notify_notes",
              "label": "Notification Notes",
              "hint": null,
              "appearance": "w12 multiline predictivetext",
              "required": null,
              "required_message": null,
              "readonly": null,
              "default": null,
              "calculation": null,
              "relevant": null,
              "choice_filter": null,
              "media::image": null,
              "bind::esri:fieldType": null,
              "bind::esri:fieldLength": 5000.0,
              "bind::esri:fieldAlias": null,
              "label_raw": "Notification Notes",
              "hint_raw": null
            }
          ]
        },
        {
          "type": "end group",
          "name": "cultural_resources_desc",
          "label": "cultural_resources_desc",
          "hint": null,
          "appearance": null,
          "required": null,
          "required_message": null,
          "readonly": null,
          "default": null,
          "calculation": null,
          "relevant": null,
          "choice_filter": null,
          "media::image": null,
          "bind::esri:fieldType": null,
          "bind::esri:fieldLength": null,
          "bind::esri:fieldAlias": null,
          "label_raw": "cultural_resources_desc",
          "hint_raw": null
        }
      ]
    },
    {
      "label": "<table cellpadding=5>\n  <tr>\n    <td valign=\"middle\"><img src=\"addForms.svg\"  height=\"35\"></td>\n    <td padding=5>\n      SWPPP<br>\n      <font size=1 color=\"navyblue\">BMPs, actions, etc.</font>\n    </td>\n  </tr>\n</table>",
      "label_raw": "SWPPP BMPs, actions, etc.",
      "items": [
        {
          "type": "select_multiple swppp_bmps",
          "name": "swppp_bmps",
          "label": "Best Management Practices (BMPs)",
          "hint": null,
          "appearance": "w12 minimal",
          "required": null,
          "required_message": null,
          "readonly": null,
          "default": null,
          "calculation": null,
          "relevant": null,
          "choice_filter": null,
          "media::image": null,
          "bind::esri:fieldType": null,
          "bind::esri:fieldLength": null,
          "bind::esri:fieldAlias": null,
          "label_raw": "Best Management Practices (BMPs)",
          "hint_raw": null
        },
        {
          "type": "select_one yes_no",
          "name": "swppp_action",
          "label": "Do BMPs require action or repair?",
          "hint": null,
          "appearance": "w12 horizontal",
          "required": null,
          "required_message": null,
          "readonly": null,
          "default": null,
          "calculation": null,
          "relevant": null,
          "choice_filter": null,
          "media::image": null,
          "bind::esri:fieldType": null,
          "bind::esri:fieldLength": null,
          "bind::esri:fieldAlias": null,
          "label_raw": "Do BMPs require action or repair?",
          "hint_raw": null
        },
        {
          "type": "text",
          "name": "swppp_actions_desc",
          "label": "Describe Actions Needed",
          "hint": null,
          "appearance": "w12 multiline predictivetext",
          "required": null,
          "required_message": null,
          "readonly": null,
          "default": null,
          "calculation": null,
          "relevant": null,
          "choice_filter": null,
          "media::image": null,
          "bind::esri:fieldType": null,
          "bind::esri:fieldLength": null,
          "bind::esri:fieldAlias": null,
          "label_raw": "Describe Actions Needed",
          "hint_raw": null
        }
      ]
    },
    {
      "label": "<table cellpadding=5>\n  <tr>\n    <td valign=\"middle\"><img src=\"addForms.svg\"  height=\"35\"></td>\n    <td padding=5>\n      Paleo Resources<br>\n      <font size=1 color=\"navyblue\">Discovery, Protections, Notifications</font>\n    </td>\n  </tr>\n</table>",
      "label_raw": "Paleo Resources Discovery, Protections, Notifications",
      "items": [
        {
          "type": "select_one yes_no",
          "name": "paleo_yn",
          "label": "Was paleo locality found during construction activities?",
          "hint": null,
          "appearance": "w1 horizontal",
          "required": null,
          "required_message": null,
          "readonly": null,
          "default": null,
          "calculation": null,
          "relevant": null,
          "choice_filter": null,
          "media::image": null,
          "bind::esri:fieldType": null,
          "bind::esri:fieldLength": null,
          "bind::esri:fieldAlias": "CR Present",
          "label_raw": "Was paleo locality found during construction activities?",
          "hint_raw": null
        },
        {
          "label": "<p>",
          "label_raw": "",
          "items": [
            {
              "type": "text",
              "name": "paleo_description",
              "label": "Description of Discovery",
              "hint": "Include relevant fossil locality or geologic unit id(s)",
              "appearance": "w12 multiline predictivetext",
              "required": null,
              "required_message": null,
              "readonly": null,
              "default": null,
              "calculation": null,
              "relevant": null,
              "choice_filter": null,
              "media::image": null,
              "bind::esri:fieldType": null,
              "bind::esri:fieldLength": 5000.0,
              "bind::esri:fieldAlias": null,
              "label_raw": "Description of Discovery",
              "hint_raw": "Include relevant fossil locality or geologic unit id(s)"
            },
            {
              "type": "select_multiple existing_protection",
              "name": "paleo_protection",
              "label": "Discovery Protection",
              "hint": null,
              "appearance": "w12 compact-2",
              "required": null,
              "required_message": null,
              "readonly": null,
              "default": null,
              "calculation": null,
              "relevant": null,
              "choice_filter": null,
              "media::image": null,
              "bind::esri:fieldType": null,
              "bind::esri:fieldLength": null,
              "bind::esri:fieldAlias": null,
              "label_raw": "Discovery Protection",
              "hint_raw": null
            },
            {
              "type": "text",
              "name": "paleo_protection_other",
              "label": "Other Protection(s)",
              "hint": null,
              "appearance": "w12 multiline predictivetext",
              "required": null,
              "required_message": null,
              "readonly": null,
              "default": null,
              "calculation": null,
              "relevant": "selected(${paleo_protection},\"other\")",
              "choice_filter": null,
              "media::image": null,
              "bind::esri:fieldType": null,
              "bind::esri:fieldLength": 5000.0,
              "bind::esri:fieldAlias": null,
              "label_raw": "Other Protection(s)",
              "hint_raw": null
            },
            {
              "type": "text",
              "name": "paleo_notify_name",
              "label": "Who was notified?",
              "hint": null,
              "appearance": "w6",
              "required": null,
              "required_message": null,
              "readonly": null,
              "default": null,
              "calculation": null,
              "relevant": null,
              "choice_filter": null,
              "media::image": null,
              "bind::esri:fieldType": null,
              "bind::esri:fieldLength": 5000.0,
              "bind::esri:fieldAlias": null,
              "label_raw": "Who was notified?",
              "hint_raw": null
            },
            {
              "type": "dateTime",
              "name": "paleo_notify_time",
              "label": "When were they notified?",
              "hint": null,
              "appearance": "w6",
              "required": null,
              "required_message": null,
              "readonly": null,
              "default": null,
              "calculation": null,
              "relevant": null,
              "choice_filter": null,
              "media::image": null,
              "bind::esri:fieldType": null,
              "bind::esri:fieldLength": null,
              "bind::esri:fieldAlias": null,
              "label_raw": "When were they notified?",
              "hint_raw": null
            },
            {
              "type": "text",
              "name": "paleo_notify_notes",
              "label": "Notification Notes",
              "hint": null,
              "appearance": "w12 multiline predictivetext",
              "required": null,
              "required_message": null,
              "readonly": null,
              "default": null,
              "calculation": null,
              "relevant": null,
              "choice_filter": null,
              "media::image": null,
              "bind::esri:fieldType": null,
              "bind::esri:fieldLength": 5000.0,
              "bind::esri:fieldAlias": null,
              "label_raw": "Notification Notes",
              "hint_raw": null
            }
          ]
        },
        {
          "type": "end group",
          "name": "paleo_resources",
          "label": "paleo_resources",
          "hint": null,
          "appearance": null,
          "required": null,
          "required_message": null,
          "readonly": null,
          "default": null,
          "calculation": null,
          "relevant": null,
          "choice_filter": null,
          "media::image": null,
          "bind::esri:fieldType": null,
          "bind::esri:fieldLength": null,
          "bind::esri:fieldAlias": null,
          "label_raw": "paleo_resources",
          "hint_raw": null
        }
      ]
    },
    {
      "label": "<table cellpadding=5>\n  <tr>\n    <td valign=\"middle\"><img src=\"addForms.svg\"  height=\"35\"></td>\n    <td padding=5>\n      Spill Inspection<br>\n      <font size=1 color=\"navyblue\">Spill Material, Cause, Amount, etc.</font>\n    </td>\n  </tr>\n</table>",
      "label_raw": "Spill Inspection Spill Material, Cause, Amount, etc.",
      "items": [
        {
          "type": "datetime",
          "name": "datetime_rep",
          "label": "Date and Time Spill was Reported: ",
          "hint": "Required Field. Record the Date and Time the Spill was Reported:",
          "appearance": "w6",
          "required": "yes",
          "required_message": null,
          "readonly": null,
          "default": "today",
          "calculation": null,
          "relevant": null,
          "choice_filter": null,
          "media::image": null,
          "bind::esri:fieldType": null,
          "bind::esri:fieldLength": null,
          "bind::esri:fieldAlias": null,
          "label_raw": "Date and Time Spill was Reported:",
          "hint_raw": "Required Field. Record the Date and Time the Spill was Reported:"
        },
        {
          "type": "select_one spill_material",
          "name": "spillmat",
          "label": "Spill Material:",
          "hint": "Required Field. Select Spill Material:",
          "appearance": "w6 minimal",
          "required": "yes",
          "required_message": null,
          "readonly": null,
          "default": null,
          "calculation": null,
          "relevant": null,
          "choice_filter": null,
          "media::image": null,
          "bind::esri:fieldType": null,
          "bind::esri:fieldLength": null,
          "bind::esri:fieldAlias": null,
          "label_raw": "Spill Material:",
          "hint_raw": "Required Field. Select Spill Material:"
        },
        {
          "type": "text",
          "name": "spillmat_oth",
          "label": "Other Spill Material:",
          "hint": "Required Field if Spill Material Selected is \"Other\" (255 character limit)",
          "appearance": "w12",
          "required": "selected(${spillmat},'other')",
          "required_message": null,
          "readonly": null,
          "default": null,
          "calculation": null,
          "relevant": null,
          "choice_filter": null,
          "media::image": null,
          "bind::esri:fieldType": null,
          "bind::esri:fieldLength": null,
          "bind::esri:fieldAlias": null,
          "label_raw": "Other Spill Material:",
          "hint_raw": "Required Field if Spill Material Selected is \"Other\" (255 character limit)"
        },
        {
          "type": "text",
          "name": "spill_cause",
          "label": "Cause of Spill:",
          "hint": "Required Field. Detail the Cause of the Spill. *",
          "appearance": "w12",
          "required": "yes",
          "required_message": null,
          "readonly": null,
          "default": null,
          "calculation": null,
          "relevant": null,
          "choice_filter": null,
          "media::image": null,
          "bind::esri:fieldType": null,
          "bind::esri:fieldLength": null,
          "bind::esri:fieldAlias": null,
          "label_raw": "Cause of Spill:",
          "hint_raw": "Required Field. Detail the Cause of the Spill. *"
        },
        {
          "type": "decimal",
          "name": "spill_amount",
          "label": "Volume of Spill Material:",
          "hint": "Required Field. Approximate volume of spill material (**NOT VOLUME OF SOIL IMPACTED**; consult with cleanup crew)",
          "appearance": "w6",
          "required": "yes",
          "required_message": null,
          "readonly": null,
          "default": null,
          "calculation": null,
          "relevant": null,
          "choice_filter": null,
          "media::image": null,
          "bind::esri:fieldType": null,
          "bind::esri:fieldLength": null,
          "bind::esri:fieldAlias": null,
          "label_raw": "Volume of Spill Material:",
          "hint_raw": "Required Field. Approximate volume of spill material (**NOT VOLUME OF SOIL IMPACTED**; consult with cleanup crew)"
        },
        {
          "type": "select_one spill_unit",
          "name": "spill_unit",
          "label": "Unit of Volume:",
          "hint": "Required Field. Select Volume Units (1 cup = 8oz):",
          "appearance": "w6 minimal",
          "required": "yes",
          "required_message": null,
          "readonly": null,
          "default": null,
          "calculation": null,
          "relevant": null,
          "choice_filter": null,
          "media::image": null,
          "bind::esri:fieldType": null,
          "bind::esri:fieldLength": null,
          "bind::esri:fieldAlias": null,
          "label_raw": "Unit of Volume:",
          "hint_raw": "Required Field. Select Volume Units (1 cup = 8oz):"
        },
        {
          "type": "text",
          "name": "spill_area",
          "label": "Area of Impact:",
          "hint": "Required Field. Length x Width OR Length x Width x Depth",
          "appearance": "w12",
          "required": "yes",
          "required_message": null,
          "readonly": null,
          "default": null,
          "calculation": null,
          "relevant": null,
          "choice_filter": null,
          "media::image": null,
          "bind::esri:fieldType": null,
          "bind::esri:fieldLength": null,
          "bind::esri:fieldAlias": null,
          "label_raw": "Area of Impact:",
          "hint_raw": "Required Field. Length x Width OR Length x Width x Depth"
        },
        {
          "type": "select_one area_unit",
          "name": "area_unit",
          "label": "Unit of Area of Impact:",
          "hint": "Approximate area and units of spill material (consult with cleanup crew)",
          "appearance": "w12 minimal",
          "required": "yes",
          "required_message": null,
          "readonly": null,
          "default": null,
          "calculation": null,
          "relevant": null,
          "choice_filter": null,
          "media::image": null,
          "bind::esri:fieldType": null,
          "bind::esri:fieldLength": null,
          "bind::esri:fieldAlias": null,
          "label_raw": "Unit of Area of Impact:",
          "hint_raw": "Approximate area and units of spill material (consult with cleanup crew)"
        },
        {
          "type": "select_one yes_no_na",
          "name": "spill_watercontact",
          "label": "Has the Spill Come Into Contact with Water Sources: ",
          "hint": "Required Field",
          "appearance": "w12 ",
          "required": "yes",
          "required_message": null,
          "readonly": null,
          "default": null,
          "calculation": null,
          "relevant": null,
          "choice_filter": null,
          "media::image": null,
          "bind::esri:fieldType": null,
          "bind::esri:fieldLength": null,
          "bind::esri:fieldAlias": null,
          "label_raw": "Has the Spill Come Into Contact with Water Sources:",
          "hint_raw": "Required Field"
        },
        {
          "type": "text",
          "name": "note_spill",
          "label": "Any Additional Information:",
          "hint": null,
          "appearance": "w12 multiline",
          "required": null,
          "required_message": null,
          "readonly": null,
          "default": null,
          "calculation": null,
          "relevant": null,
          "choice_filter": null,
          "media::image": null,
          "bind::esri:fieldType": null,
          "bind::esri:fieldLength": null,
          "bind::esri:fieldAlias": null,
          "label_raw": "Any Additional Information:",
          "hint_raw": null
        },
        {
          "type": "select_one rain",
          "name": "rain_event",
          "label": "Rain Event(typically >0.25\"/24hrs or >0.5\"/24hrs, state specific):",
          "hint": null,
          "appearance": "w6 minimal",
          "required": null,
          "required_message": null,
          "readonly": null,
          "default": null,
          "calculation": null,
          "relevant": null,
          "choice_filter": null,
          "media::image": null,
          "bind::esri:fieldType": null,
          "bind::esri:fieldLength": null,
          "bind::esri:fieldAlias": null,
          "label_raw": "Rain Event(typically >0.25\"/24hrs or >0.5\"/24hrs, state specific):",
          "hint_raw": null
        },
        {
          "type": "select_multiple response",
          "name": "response",
          "label": "Spill Response Actions:",
          "hint": "Required Field. Select All Spill Actions that Apply:",
          "appearance": "w12 compact",
          "required": "yes",
          "required_message": null,
          "readonly": null,
          "default": null,
          "calculation": null,
          "relevant": null,
          "choice_filter": null,
          "media::image": null,
          "bind::esri:fieldType": null,
          "bind::esri:fieldLength": null,
          "bind::esri:fieldAlias": null,
          "label_raw": "Spill Response Actions:",
          "hint_raw": "Required Field. Select All Spill Actions that Apply:"
        },
        {
          "type": "text",
          "name": "response_oth",
          "label": "Other Responses:",
          "hint": "Required Field if Response is \"Other\" (255 character limit)",
          "appearance": "w12",
          "required": "selected(${response},'other')",
          "required_message": null,
          "readonly": null,
          "default": null,
          "calculation": null,
          "relevant": null,
          "choice_filter": null,
          "media::image": null,
          "bind::esri:fieldType": null,
          "bind::esri:fieldLength": null,
          "bind::esri:fieldAlias": null,
          "label_raw": "Other Responses:",
          "hint_raw": "Required Field if Response is \"Other\" (255 character limit)"
        },
        {
          "type": "select_one yes_no_na",
          "name": "further_actions",
          "label": "Further Actions:",
          "hint": "Required Field. Are further actions required?",
          "appearance": "w12 minimal",
          "required": "yes",
          "required_message": null,
          "readonly": null,
          "default": null,
          "calculation": null,
          "relevant": null,
          "choice_filter": null,
          "media::image": null,
          "bind::esri:fieldType": null,
          "bind::esri:fieldLength": null,
          "bind::esri:fieldAlias": null,
          "label_raw": "Further Actions:",
          "hint_raw": "Required Field. Are further actions required?"
        },
        {
          "type": "text",
          "name": "note_actions",
          "label": "Describe Additional Actions:",
          "hint": "Required Field if Further Actions Selected is \"Yes\" (255 character limit)",
          "appearance": "w12",
          "required": "selected(${further_actions},'yes')",
          "required_message": null,
          "readonly": null,
          "default": null,
          "calculation": null,
          "relevant": null,
          "choice_filter": null,
          "media::image": null,
          "bind::esri:fieldType": null,
          "bind::esri:fieldLength": null,
          "bind::esri:fieldAlias": null,
          "label_raw": "Describe Additional Actions:",
          "hint_raw": "Required Field if Further Actions Selected is \"Yes\" (255 character limit)"
        }
      ]
    },
    {
      "type": "begin repeat",
      "name": "monitoring_photo",
      "label": "<table cellpadding=5>\n  <tr>\n    <td valign=\"middle\"><img src=\"camera.svg\"  height=\"35\"></td>\n    <td padding=5>\n      Photo Log<br>\n      <font size=1 color=\"navyblue\">Click the \"Add\" button</b> (\"+\" icon) to record multiple photos. Each photo will be associated with a point at your current location.</font>\n    </td>\n  </tr>\n</table>",
      "hint": null,
      "appearance": "w12 minimal compact",
      "required": null,
      "required_message": null,
      "readonly": null,
      "default": null,
      "calculation": null,
      "relevant": null,
      "choice_filter": null,
      "media::image": null,
      "bind::esri:fieldType": null,
      "bind::esri:fieldLength": null,
      "bind::esri:fieldAlias": null,
      "label_raw": "Photo Log Click the \"Add\" button (\"+\" icon) to record multiple photos. Each photo will be associated with a point at your current location.",
      "hint_raw": null
    },
    {
      "type": "geopoint",
      "name": "photo_location",
      "label": "Photo Location",
      "hint": null,
      "appearance": "w12",
      "required": null,
      "required_message": null,
      "readonly": null,
      "default": null,
      "calculation": null,
      "relevant": null,
      "choice_filter": null,
      "media::image": null,
      "bind::esri:fieldType": null,
      "bind::esri:fieldLength": null,
      "bind::esri:fieldAlias": null,
      "label_raw": "Photo Location",
      "hint_raw": null
    },
    {
      "type": "hidden",
      "name": "photo_no",
      "label": "Photo Number",
      "hint": null,
      "appearance": "w12",
      "required": null,
      "required_message": null,
      "readonly": null,
      "default": null,
      "calculation": "position(..)",
      "relevant": null,
      "choice_filter": null,
      "media::image": null,
      "bind::esri:fieldType": null,
      "bind::esri:fieldLength": null,
      "bind::esri:fieldAlias": null,
      "label_raw": "Photo Number",
      "hint_raw": null
    },
    {
      "type": "image",
      "name": "photo",
      "label": "Record a Photo",
      "hint": null,
      "appearance": "w12",
      "required": null,
      "required_message": null,
      "readonly": null,
      "default": null,
      "calculation": null,
      "relevant": null,
      "choice_filter": null,
      "media::image": null,
      "bind::esri:fieldType": null,
      "bind::esri:fieldLength": null,
      "bind::esri:fieldAlias": null,
      "label_raw": "Record a Photo",
      "hint_raw": null
    },
    {
      "type": "text",
      "name": "photo_label",
      "label": "Photograph Number/Label",
      "hint": null,
      "appearance": "w12",
      "required": null,
      "required_message": null,
      "readonly": null,
      "default": null,
      "calculation": "concat\n(if(${project_id}=\"\",\"\",concat(${project_id}))\n,\nif(${photo_direction}=\"\",\"\",concat(${photo_direction},\"_\")),${photo_no})",
      "relevant": null,
      "choice_filter": null,
      "media::image": null,
      "bind::esri:fieldType": null,
      "bind::esri:fieldLength": 255.0,
      "bind::esri:fieldAlias": null,
      "label_raw": "Photograph Number/Label",
      "hint_raw": null
    },
    {
      "type": "select_one list_photographs_camera_facing",
      "name": "photo_direction",
      "label": "Direction",
      "hint": null,
      "appearance": "w6 compact-3",
      "required": null,
      "required_message": null,
      "readonly": null,
      "default": null,
      "calculation": null,
      "relevant": null,
      "choice_filter": null,
      "media::image": null,
      "bind::esri:fieldType": null,
      "bind::esri:fieldLength": 255.0,
      "bind::esri:fieldAlias": null,
      "label_raw": "Direction",
      "hint_raw": null
    },
    {
      "type": "hidden",
      "name": "photo_quality",
      "label": "Photo Width x Length",
      "hint": null,
      "appearance": "w6",
      "required": null,
      "required_message": null,
      "readonly": null,
      "default": null,
      "calculation": "concat(pulldata(\"@exif\", ${photo}, \"ImageWidth\"),\" x \", pulldata(\"@exif\", ${photo}, \"ImageLength\"))",
      "relevant": null,
      "choice_filter": null,
      "media::image": null,
      "bind::esri:fieldType": null,
      "bind::esri:fieldLength": null,
      "bind::esri:fieldAlias": null,
      "label_raw": "Photo Width x Length",
      "hint_raw": null
    },
    {
      "type": "text",
      "name": "photograph_description",
      "label": "Photograph Description",
      "hint": null,
      "appearance": "w12 multiline",
      "required": null,
      "required_message": null,
      "readonly": null,
      "default": null,
      "calculation": null,
      "relevant": null,
      "choice_filter": null,
      "media::image": null,
      "bind::esri:fieldType": null,
      "bind::esri:fieldLength": 1000.0,
      "bind::esri:fieldAlias": null,
      "label_raw": "Photograph Description",
      "hint_raw": null
    },
    {
      "type": "end repeat",
      "name": "monitoring_photo",
      "label": "monitoring_photo",
      "hint": null,
      "appearance": null,
      "required": null,
      "required_message": null,
      "readonly": null,
      "default": null,
      "calculation": null,
      "relevant": null,
      "choice_filter": null,
      "media::image": null,
      "bind::esri:fieldType": null,
      "bind::esri:fieldLength": null,
      "bind::esri:fieldAlias": null,
      "label_raw": "monitoring_photo",
      "hint_raw": null
    }
  ]
}
